{
    "description": "Inquiring minds want to know what benefits them in each new release of Flash\nProfessional CC. In this course, Anastasia McCune answers your most burning\nquestions. Learn about the interface changes and performance improvements that\ncome with this update, plus the new Code Editor, JSAPI improvements, and\nmobile testing enhancements.  \n  \nNote: Adobe Creative Cloud is updated on a regular basis. We will add more\ntutorials as features are added or changed, so check back often.",
    "instructors": "Anastasia McCune",
    "url": "https:\/\/www.coursetalk.com\/providers\/lynda\/courses\/flash-professional-creative-cloud-updates",
    "title": "Flash Professional: Creative Cloud Updates",
    "language": "en",
    "source": "coursetalk"
}